autoauditor/__init__.py
autoauditor/__main__.py
autoauditor/blockchain.py
autoauditor/constants.py
autoauditor/metasploit.py
autoauditor/query.py
autoauditor/utils.py
autoauditor/vpn.py
autoauditor/wizard.py
autoauditor/gui/__init__.py
autoauditor/gui/gui.py
autoauditor/gui/resources.py
autoauditor-3.1.2.dist-info/LICENSE
autoauditor-3.1.2.dist-info/METADATA
autoauditor-3.1.2.dist-info/WHEEL
autoauditor-3.1.2.dist-info/entry_points.txt
autoauditor-3.1.2.dist-info/top_level.txt
autoauditor-3.1.2.dist-info/RECORD
