Metadata-Version: 2.1
Name: autoauditor
Version: 3.1.2
Summary: Semi-automatic scanner and vulnerability exploiter
Home-page: https://gitlab.gast.it.uc3m.es/schica/autoauditor
Author: Sergio Chica
Author-email: sergio.chica@uc3m.es
License: GPLv3+
Keywords: vulnerability,metasploit,exploit,scanner,nmap,cve
Platform: UNKNOWN
Classifier: License :: OSI Approved :: GNU General Public License v3 or later (GPLv3+)
Classifier: Programming Language :: Python :: 3
Classifier: Programming Language :: Python :: 3.8
Requires-Python: >= 3.8
License-File: LICENSE
Requires-Dist: aiogrpc (==1.8)
Requires-Dist: appdirs (==1.4.4)
Requires-Dist: beautifulsoup4 (==4.11.1)
Requires-Dist: bs4 (==0.0.1)
Requires-Dist: certifi (==2022.5.18.1)
Requires-Dist: cffi (==1.15.0)
Requires-Dist: chardet (==3.0.4)
Requires-Dist: click (==8.1.3)
Requires-Dist: CouchDB (==1.2)
Requires-Dist: cryptography (==37.0.2)
Requires-Dist: decorator (==5.1.1)
Requires-Dist: docker (==5.0.3)
Requires-Dist: Flask (==2.1.2)
Requires-Dist: gitdb (==4.0.9)
Requires-Dist: GitPython (==3.1.27)
Requires-Dist: grpcio (==1.46.3)
Requires-Dist: hkdf (==0.0.3)
Requires-Dist: idna (==2.7)
Requires-Dist: importlib-metadata (==4.11.4)
Requires-Dist: itsdangerous (==2.1.2)
Requires-Dist: Jinja2 (==3.1.2)
Requires-Dist: lark-parser (==0.7.1)
Requires-Dist: MarkupSafe (==2.1.1)
Requires-Dist: msgpack (==1.0.4)
Requires-Dist: opentimestamps (==0.4.1)
Requires-Dist: opentimestamps-client (==0.7.0)
Requires-Dist: path (==16.4.0)
Requires-Dist: path.py (==12.5.0)
Requires-Dist: protobuf (==3.20.1)
Requires-Dist: py (==1.11.0)
Requires-Dist: pycparser (==2.21)
Requires-Dist: pycryptodomex (==3.14.1)
Requires-Dist: pyOpenSSL (==22.0.0)
Requires-Dist: pysha3 (==1.0.2)
Requires-Dist: PySide6 (==6.3.0)
Requires-Dist: PySide6-Addons (==6.3.0)
Requires-Dist: PySide6-Essentials (==6.3.0)
Requires-Dist: PySocks (==1.7.1)
Requires-Dist: python-bitcoinlib (==0.10.2)
Requires-Dist: requests (==2.20.0)
Requires-Dist: retry (==0.9.2)
Requires-Dist: Rx (==3.2.0)
Requires-Dist: shiboken6 (==6.3.0)
Requires-Dist: six (==1.16.0)
Requires-Dist: smmap (==5.0.0)
Requires-Dist: soupsieve (==2.3.2.post1)
Requires-Dist: urllib3 (==1.24.3)
Requires-Dist: websocket-client (==1.3.2)
Requires-Dist: Werkzeug (==2.1.2)
Requires-Dist: zipp (==3.8.0)
